LeafPy/__init__.py
LeafPy/conf/__init__.py
LeafPy/conf/global_settings.py
LeafPy/db/__init__.py
LeafPy/db/client.py
LeafPy/examples/__init__.py
LeafPy/examples/settings.py
LeafPy/examples/urls.py
LeafPy/examples/wsgi.py
LeafPy/examples/index/__init__.py
LeafPy/examples/index/actions.py
LeafPy/examples/index/rndcode.py
LeafPy/examples/media/main.css
LeafPy/examples/templates/hello.html
LeafPy/examples/views/imgcode.html
LeafPy/examples/views/jinja.html
LeafPy/examples/views/mako.html
LeafPy/examples/views/upload.html
LeafPy/handlers/__init__.py
LeafPy/handlers/application.py
LeafPy/handlers/httpserver.py
LeafPy/handlers/session.py
LeafPy/handlers/wsgi.py
LeafPy/http/__init__.py
LeafPy/http/debugerror.py
LeafPy/http/resultstruct.py
LeafPy/middleware/__init__.py
LeafPy/middleware/log.py
LeafPy/middleware/static.py
LeafPy/template/__init__.py
LeafPy/template/_compiler.py
LeafPy/template/_render.py
LeafPy/template/_template.py
LeafPy/template/contrib/__init__.py
LeafPy/template/contrib/template.py
LeafPy/utils/__init__.py
LeafPy/utils/datastructs.py
LeafPy/utils/encoding.py
LeafPy/utils/imgcode.py
LeafPy/utils/importlib.py
LeafPy/utils/net.py
LeafPy/utils/py3helpers.py
leaf.py-1.1.1.data/scripts/LeafPy-admin.py
leaf.py-1.1.1.dist-info/LICENSE
leaf.py-1.1.1.dist-info/METADATA
leaf.py-1.1.1.dist-info/WHEEL
leaf.py-1.1.1.dist-info/top_level.txt
leaf.py-1.1.1.dist-info/RECORD
