Metadata-Version: 2.1
Name: leaf.py
Version: 1.1.1
Summary: a mini python web framework
Home-page: https://www.leafpy.org
Author: Huaqing Ye
Author-email: yhq1978@yahoo.com
License: MIT License
Keywords: leaf.py,leaf.py web framework
Platform: any
Classifier: Programming Language :: Python
Classifier: Programming Language :: Python :: 2.7
Classifier: Programming Language :: Python :: 3
Classifier: Programming Language :: Python :: 3.5
Classifier: Programming Language :: Python :: 3.6
Classifier: Programming Language :: Python :: 3.7
Classifier: Programming Language :: Python :: 3.8
Requires-Python: >=2.7
Requires-Dist: sqlalchemy
Requires-Dist: cheroot
